tdds/__init__.py
tdds/basics.py
tdds/cleaner.py
tdds/collections.py
tdds/marshaller.py
tdds/pods.py
tdds/record.py
tdds/shortcuts.py
tdds/unpickler.py
tdds/utils/__init__.py
tdds/utils/builder.py
tdds/utils/codegen.py
tdds/utils/compatibility.py
tdds/utils/immutabledict.py
tests/__init__.py
tests/check_tests.py
tests/cleaner_tests.py
tests/coercion_tests.py
tests/collection_tests.py
tests/core_tests.py
tests/marshaller_tests.py
tests/pickle_tests.py
tests/plumbing.py
tests/pods_tests.py
tests/readme_tests.py
tests/recursive_types_tests.py
tests/run.py
tests/shortcut_tests.py
tests/subclassing_tests.py
tdds-1.0.dist-info/METADATA
tdds-1.0.dist-info/WHEEL
tdds-1.0.dist-info/top_level.txt
tdds-1.0.dist-info/RECORD
