Metadata-Version: 2.1
Name: tdds
Version: 1.0
Summary: Typed, declarative data structures
Home-page: https://github.com/saintamh/tdds/
Author: Hervé Saint-Amand
Author-email: tdds@saintamh.org
License: UNKNOWN
Platform: UNKNOWN
Classifier: License :: OSI Approved :: MIT License
Classifier: Operating System :: OS Independent
Classifier: Programming Language :: Python :: 3
Classifier: Topic :: Software Development :: Libraries
